wraptimer/__init__.py
wraptimer/timeit.py
wraptimer/timer.py
wraptimer/utils.py
wraptimer-0.1.2.dist-info/METADATA
wraptimer-0.1.2.dist-info/WHEEL
wraptimer-0.1.2.dist-info/RECORD
