Metadata-Version: 2.1
Name: wraptimer
Version: 0.1.2
Summary: An amazing alternative to Python's builtin timeit module that allows for high resolution timing of functions as well as in-depth line-by-line timing. It also exposes convenient classes to measure execution time for any arbitrary code.
Home-page: https://mugendi.github.io/wraptimer/
License: MIT
Keywords: function,time,duration,trace,timer,timeit
Author: Anthony Mugendi
Author-email: ngurumugz@gmail.com
Requires-Python: >=3.9,<4.0
Classifier: License :: OSI Approved :: MIT License
Classifier: Programming Language :: Python :: 3
Classifier: Programming Language :: Python :: 3.9
Classifier: Programming Language :: Python :: 3.10
Classifier: Programming Language :: Python :: 3.11
Classifier: Topic :: Software Development :: Debuggers
Classifier: Topic :: Software Development :: Libraries :: Python Modules
Classifier: Topic :: Software Development :: Testing
Requires-Dist: termcolor (>=2.3.0,<3.0.0)
Project-URL: Repository, https://github.com/mugendi/wraptimer
